scrapy_cdr/__init__.py
scrapy_cdr/es_download.py
scrapy_cdr/es_download_hashes.py
scrapy_cdr/es_upload.py
scrapy_cdr/items.py
scrapy_cdr/media_pipeline.py
scrapy_cdr/utils.py
scrapy_cdr/v2_to_v3.py
scrapy_cdr-0.5.1.dist-info/DESCRIPTION.rst
scrapy_cdr-0.5.1.dist-info/METADATA
scrapy_cdr-0.5.1.dist-info/RECORD
scrapy_cdr-0.5.1.dist-info/WHEEL
scrapy_cdr-0.5.1.dist-info/entry_points.txt
scrapy_cdr-0.5.1.dist-info/metadata.json
scrapy_cdr-0.5.1.dist-info/top_level.txt
